simplevis/__init__.py
simplevis/vis.py
simple_vis-0.1.2.dist-info/LICENSE.md
simple_vis-0.1.2.dist-info/METADATA
simple_vis-0.1.2.dist-info/WHEEL
simple_vis-0.1.2.dist-info/top_level.txt
simple_vis-0.1.2.dist-info/RECORD
