Metadata-Version: 2.1
Name: simple-vis
Version: 0.1.2
Summary: Simple image visualize tool
Home-page: UNKNOWN
Author: UNKNOWN
Author-email: UNKNOWN
License: UNKNOWN
Platform: UNKNOWN
